roboenum/__init__.py
roboenum/cli.py
roboenum-0.1.3.dist-info/METADATA
roboenum-0.1.3.dist-info/WHEEL
roboenum-0.1.3.dist-info/entry_points.txt
roboenum-0.1.3.dist-info/top_level.txt
roboenum-0.1.3.dist-info/RECORD
