Metadata-Version: 2.4
Name: roboenum
Version: 0.1.3
Summary: A robots.txt network enumeration and fingerprinting tool
Home-page: https://github.com/QTShade/roboenum
Author: QTShade
License: MIT
Keywords: roboenum,enum,recon,tools,pentest
Classifier: Programming Language :: Python :: 3
Classifier: License :: OSI Approved :: MIT License
Classifier: Operating System :: OS Independent
Requires-Python: >=3.8
Requires-Dist: httpx
Requires-Dist: colorama
Dynamic: author
Dynamic: classifier
Dynamic: home-page
Dynamic: keywords
Dynamic: license
Dynamic: requires-dist
Dynamic: requires-python
Dynamic: summary
